<?xml version="1.0" encoding="UTF-8"?>
<signed on="5-Apr-2020 7:40:21 PM">
  <stylesheets>
    <stylesheet name="oasis-specification-fo-us.xsl" md5="h8LEH9gorOrAPG30K9r9oQ=="/>
    <stylesheet name="oasis-specification-fo-a4.xsl" md5="4XhAWcs4xXfYlci/AuBBAg=="/>
    <stylesheet name="../../spec-0.8/docbook/xsl/fo/docbook.xsl" md5="HTM7LhUiJnjQ9pBLYQvvtQ=="/>
    <stylesheet name="../../spec-0.8/docbook/xsl/VERSION.xsl" md5="2cwpOvxW0Kf4kLbyyObdfw=="/>
    <stylesheet name="../../spec-0.8/docbook/xsl/fo/param.xsl" md5="uFzsyMdGO0ov2zbbaDODsA=="/>
    <stylesheet name="../../spec-0.8/docbook/xsl/lib/lib.xsl" md5="QiN4FX5xAa81g7uypW+9Fg=="/>
    <stylesheet name="../../spec-0.8/docbook/xsl/common/l10n.xsl" md5="0SG/VSynUYQNxXLBsosA5g=="/>
    <stylesheet name="../../spec-0.8/docbook/xsl/common/common.xsl" md5="DLfsFeZ70S7l2qH5FYTsnQ=="/>
    <stylesheet name="../../spec-0.8/docbook/xsl/common/utility.xsl" md5="bDEZ5ZnFP/Yv6IzFmjwL3g=="/>
    <stylesheet name="../../spec-0.8/docbook/xsl/common/labels.xsl" md5="tNyf/3kZd347CYDU5org6A=="/>
    <stylesheet name="../../spec-0.8/docbook/xsl/common/titles.xsl" md5="RH4aIuU1CQYDu9O6OaVwiQ=="/>
    <stylesheet name="../../spec-0.8/docbook/xsl/common/subtitles.xsl" md5="nnlaPByV5PTyEdF57R3Afg=="/>
    <stylesheet name="../../spec-0.8/docbook/xsl/common/gentext.xsl" md5="JPwmN7REbDPWc/Kh9mkuTA=="/>
    <stylesheet name="../../spec-0.8/docbook/xsl/common/olink.xsl" md5="iZUuUizbtyrOdu03WXdmoA=="/>
    <stylesheet name="../../spec-0.8/docbook/xsl/common/targets.xsl" md5="D/2DYaBSahSLNLJGMz79vA=="/>
    <stylesheet name="../../spec-0.8/docbook/xsl/common/pi.xsl" md5="ladx/k19B0Vl9Jve20/CrA=="/>
    <stylesheet name="../../spec-0.8/docbook/xsl/fo/autotoc.xsl" md5="KASJgUFI3ydWsPXdwDRNqA=="/>
    <stylesheet name="../../spec-0.8/docbook/xsl/fo/autoidx.xsl" md5="akd5tldbR3IhuIUsrqLxKQ=="/>
    <stylesheet name="../../spec-0.8/docbook/xsl/fo/lists.xsl" md5="NV0dk12e4ny2A99o0MzsVA=="/>
    <stylesheet name="../../spec-0.8/docbook/xsl/fo/callout.xsl" md5="d5VQ4kKSG2p0+6430nwkmw=="/>
    <stylesheet name="../../spec-0.8/docbook/xsl/fo/verbatim.xsl" md5="OQsYm78ASLJ0gcamgr6C+g=="/>
    <stylesheet name="../../spec-0.8/docbook/xsl/fo/graphics.xsl" md5="vDvM6HR2Yt0+qTpnBRzdhA=="/>
    <stylesheet name="../../spec-0.8/docbook/xsl/fo/xref.xsl" md5="sa+ptPvQ/0onrba42DA+TQ=="/>
    <stylesheet name="../../spec-0.8/docbook/xsl/fo/formal.xsl" md5="HEIEhqrp2At/ekabZhiTrw=="/>
    <stylesheet name="../../spec-0.8/docbook/xsl/fo/table.xsl" md5="a+S0Vij28CxJZgmxbLoQHQ=="/>
    <stylesheet name="../../spec-0.8/docbook/xsl/common/table.xsl" md5="cEQpV1btZvTRcJ5stwfvRw=="/>
    <stylesheet name="../../spec-0.8/docbook/xsl/fo/htmltbl.xsl" md5="r+ZFMgu4j4lYnmKV7FDZpg=="/>
    <stylesheet name="../../spec-0.8/docbook/xsl/fo/sections.xsl" md5="4cCnnozFMj0UhH4mp5X2VA=="/>
    <stylesheet name="../../spec-0.8/docbook/xsl/fo/inline.xsl" md5="cN+iRsKXDNgxaFsCsRBL3Q=="/>
    <stylesheet name="../../spec-0.8/docbook/xsl/fo/footnote.xsl" md5="kFP+pj2mWna+JSiDUqXzRw=="/>
    <stylesheet name="../../spec-0.8/docbook/xsl/fo/fo.xsl" md5="0NjRm836tMtkS7FPb4NPBA=="/>
    <stylesheet name="../../spec-0.8/docbook/xsl/fo/fo-rtf.xsl" md5="Byi2/sVs8uk7A6SgnGm7Ag=="/>
    <stylesheet name="../../spec-0.8/docbook/xsl/fo/info.xsl" md5="83qq9ra/Se8t5VWynFdVhA=="/>
    <stylesheet name="../../spec-0.8/docbook/xsl/fo/keywords.xsl" md5="HOYeCapwhZu8KW4BnIU+BQ=="/>
    <stylesheet name="../../spec-0.8/docbook/xsl/fo/division.xsl" md5="zaWEjhJdAwmOIhZjgjGwiQ=="/>
    <stylesheet name="../../spec-0.8/docbook/xsl/fo/index.xsl" md5="DO3Z/xWMoTxtMrrQf8ZVYQ=="/>
    <stylesheet name="../../spec-0.8/docbook/xsl/fo/toc.xsl" md5="bQMCwIWGgYDnWVPUVYmR/w=="/>
    <stylesheet name="../../spec-0.8/docbook/xsl/fo/refentry.xsl" md5="XTiyTVRMCeMmymNk6g8k8Q=="/>
    <stylesheet name="../../spec-0.8/docbook/xsl/fo/math.xsl" md5="KNUPWKXOxY6crnJdyBscxA=="/>
    <stylesheet name="../../spec-0.8/docbook/xsl/fo/admon.xsl" md5="0ViHw2H+kWCBuI3e4DZbpA=="/>
    <stylesheet name="../../spec-0.8/docbook/xsl/fo/component.xsl" md5="JOcGfRafq+d1RaCsYNKe5A=="/>
    <stylesheet name="../../spec-0.8/docbook/xsl/fo/biblio.xsl" md5="zRADNNz1+bQbJs7ZBwdmNA=="/>
    <stylesheet name="../../spec-0.8/docbook/xsl/fo/biblio-iso690.xsl" md5="dXLf90Eliyi+IBkqEzChJg=="/>
    <stylesheet name="../../spec-0.8/docbook/xsl/fo/glossary.xsl" md5="XLwMGX4vhP57FGojWiTxGg=="/>
    <stylesheet name="../../spec-0.8/docbook/xsl/fo/block.xsl" md5="U7Cpi78M1bna2xMOELDHpA=="/>
    <stylesheet name="../../spec-0.8/docbook/xsl/fo/task.xsl" md5="xha5U6xzLhzC5Sad6n8/rA=="/>
    <stylesheet name="../../spec-0.8/docbook/xsl/fo/qandaset.xsl" md5="mbhus3xo5crhSvnTwQYD1g=="/>
    <stylesheet name="../../spec-0.8/docbook/xsl/fo/synop.xsl" md5="+2p8WVg7HOgk5HA0vlCWJQ=="/>
    <stylesheet name="../../spec-0.8/docbook/xsl/fo/titlepage.xsl" md5="/Q27hMqj49LUh+P+95wkuw=="/>
    <stylesheet name="../../spec-0.8/docbook/xsl/fo/titlepage.templates.xsl" md5="Di0IYq4oYzzLgFMMuGJ7PA=="/>
    <stylesheet name="../../spec-0.8/docbook/xsl/fo/pagesetup.xsl" md5="9zVbud3l8keL+g5xFEzTPg=="/>
    <stylesheet name="../../spec-0.8/docbook/xsl/fo/pi.xsl" md5="hshLDVDtwJutCdzKUPpP2A=="/>
    <stylesheet name="../../spec-0.8/docbook/xsl/fo/spaces.xsl" md5="vzXHYAs5AKujjQMehuxPug=="/>
    <stylesheet name="../../spec-0.8/docbook/xsl/fo/ebnf.xsl" md5="AXDhluDDc0U7SgGN8I4Jag=="/>
    <stylesheet name="../../spec-0.8/docbook/xsl/html/chunker.xsl" md5="S2zERzgdeTyG5LHO8A8lWw=="/>
    <stylesheet name="../../spec-0.8/docbook/xsl/fo/annotations.xsl" md5="XhLSE8UegVg8M5ZEjmWkUQ=="/>
    <stylesheet name="../../spec-0.8/docbook/xsl/fo/publishers.xsl" md5="3+sl9Was3Vnib1Esy7En9w=="/>
    <stylesheet name="../../spec-0.8/docbook/xsl/common/stripns.xsl" md5="ZtdaZh3wtSChK8I5mOwv7g=="/>
    <stylesheet name="../../spec-0.8/docbook/xsl/fo/fop.xsl" md5="iAFQftSlpvOgQnzZaMEYmg=="/>
    <stylesheet name="../../spec-0.8/docbook/xsl/fo/fop1.xsl" md5="kGbNDmSNN8xloKsA/tgFNg=="/>
    <stylesheet name="../../spec-0.8/docbook/xsl/fo/xep.xsl" md5="SVmdzKEZ/34RbbR1LxCyaQ=="/>
    <stylesheet name="../../spec-0.8/docbook/xsl/fo/axf.xsl" md5="O0p3m4zpPhfx2ulp0c6Xeg=="/>
    <stylesheet name="../../spec-0.8/docbook/xsl/fo/ptc.xsl" md5="MLLzYQIFizCr+LSIL14gnw=="/>
    <stylesheet name="titlepage-fo.xsl" md5="3CW1vvMhl2jY7kRnTm/GJQ=="/>
    <stylesheet name="oasis-mathml-fo.xsl" md5="qGgNUQTl42qBSWF4KZh/ng=="/>
  </stylesheets>
  <sig md5="g6ttyG50dqjsth0xUY2vpg==" signature="MCwCFDTSYgyxsQx/ym23IDnAgK5U84fPAhQ3YniH91vWVGuA7HItgR1bzgkhMg==">
  </sig>
</signed>
